Workbook

Sheet Instructions
A1: MULTI-JURISDICTION FILING TRACKER
A3: Purpose
A4: This tool tracks GloBE Information Return (GIR) filing status across all jurisdictions where your MNE group has Pillar Two obligations.
A6: Based On
A7: • OECD GIR Template and XML Schema (January 2025)
A8: • GIR Multilateral Competent Authority Agreement (MCAA) framework
A9: • Multi-Jurisdiction Filing Coordination Framework per OECD Administrative Guidance
A11: Worksheet Overview
A12: 1. Instructions | C12: This overview and guidance
A13: 2. Group_Info | C13: MNE group identification and fiscal year details
A14: 3. Jurisdiction_Inventory | C14: List all jurisdictions with Pillar Two presence
A15: 4. Deadline_Matrix | C15: Registration, GIR, domestic return, and payment deadlines
A16: 5. Responsibility_Assignment | C16: Responsible persons and advisers by jurisdiction
A17: 6. Obligation_Mapping | C17: Detailed obligation mapping per jurisdiction
A18: 7. Primary_Filing_Prep | C18: Primary filing preparation checklist
A19: 8. XML_Preparation | C19: Multi-jurisdiction XML preparation checklist
A20: 9. Submission_Tracker | C20: Track all GIR and notification submissions
A21: 10. QDMTT_Returns | C21: Track QDMTT and domestic return filings
A22: 11. Post_Filing_Verification | C22: Post-filing verification checklist
A23: 12. Amendment_Tracker | C23: Amendment coordination tracking
... A25: 14. Sign_Off | C25: Sign-off and certification
A28: Color Coding
A29: Yellow cells | C29: Input cells - enter your data here
A30: Green cells | C30: Calculated/auto-populated cells
A31: Blue header | C31: Section headers
A33: Version: 1.0 | Created: December 2025 | OECD Schema: January 2025

Sheet Group_Info
A1: MNE GROUP INFORMATION
A3: Group Name:
A4: Ultimate Parent Entity (UPE):
A5: UPE Jurisdiction:
A6: UPE Tax ID Number:
A7: Primary Filing Jurisdiction:
A8: Fiscal Year Start:
A9: Fiscal Year End:
A10: First Year in Scope:
A11: Number of Jurisdictions:
A12: Number of Constituent Entities:
A13: Designated Filing Entity (if different from UPE):
... A20: FILING DEADLINE CALCULATION
A22: Fiscal Year End: | B22: =B9
A23: First Year Filing Deadline (18 months): | B23: =IF(B9="","",DATE(YEAR(B9)+1,MONTH(B9)+6,DAY(B9)))
A24: Standard Deadline (15 months, Year 2+): | B24: =IF(B9="","",DATE(YEAR(B9)+1,MONTH(B9)+3,DAY(B9)))
A26: Note: First GIR deadline cannot be before 30 June 2026 per OECD Administrative Guidance

Sheet Jurisdiction_Inventory
A1: JURISDICTION INVENTORY
A2: List all jurisdictions where the MNE group has Pillar Two presence or filing obligations
A4: # | B4: Jurisdiction | C4: Filing Status | D4: Pillar Two Implemented? | E4: MCAA Signatory? | F4: IIR Effective? | G4: UTPR Effective? | H4: QDMTT Effective?
A5: 1 | B5: United Kingdom
A6: 2 | B6: Germany
A7: 3 | B7: Netherlands
A8: 4 | B8: France
A9: 5 | B9: Ireland
A10: 6 | B10: Luxembourg
A11: 7 | B11: Switzerland
A12: 8 | B12: Austria
A13: 9 | B13: Belgium
A14: 10 | B14: Italy
A15: 11 | B15: Spain
A16: 12 | B16: Denmark
... A29: 25 | B29: New Zealand
A30: 26
A31: 27
A32: 28
A33: 29
A34: 30

Sheet Deadline_Matrix
A1: DEADLINE MATRIX
A3: Jurisdiction | B3: Registration Deadline | C3: GIR/Notification Deadline | D3: Domestic Return Deadline | E3: Payment Deadline | F3: Extension Available? | G3: Notes
A4: =Jurisdiction_Inventory!B5
A5: =Jurisdiction_Inventory!B6
A6: =Jurisdiction_Inventory!B7
A7: =Jurisdiction_Inventory!B8
A8: =Jurisdiction_Inventory!B9
A9: =Jurisdiction_Inventory!B10
A10: =Jurisdiction_Inventory!B11
A11: =Jurisdiction_Inventory!B12
A12: =Jurisdiction_Inventory!B13
A13: =Jurisdiction_Inventory!B14
A14: =Jurisdiction_Inventory!B15
A15: =Jurisdiction_Inventory!B16
... A33: =Jurisdiction_Inventory!B34

Sheet Responsibility_Assignment
A1: RESPONSIBILITY ASSIGNMENT
A3: Jurisdiction | B3: Responsible Person | C3: Email | D3: Backup Contact | E3: External Adviser | F3: Adviser Contact
A4: =Jurisdiction_Inventory!B5
A5: =Jurisdiction_Inventory!B6
A6: =Jurisdiction_Inventory!B7
A7: =Jurisdiction_Inventory!B8
A8: =Jurisdiction_Inventory!B9
A9: =Jurisdiction_Inventory!B10
A10: =Jurisdiction_Inventory!B11
A11: =Jurisdiction_Inventory!B12
A12: =Jurisdiction_Inventory!B13
A13: =Jurisdiction_Inventory!B14
A14: =Jurisdiction_Inventory!B15
A15: =Jurisdiction_Inventory!B16
... A33: =Jurisdiction_Inventory!B34

Sheet Obligation_Mapping
A1: OBLIGATION MAPPING
A2: Detailed analysis of filing obligations per jurisdiction
A4: Jurisdiction | B4: Filing Requirement | C4: Filing Entity | D4: MCAA Exchange? | E4: Registration Required? | F4: Registration Complete? | G4: Portal Access Confirmed? | H4: QDMTT Return Required? | I4: IIR/UTPR Return Required?
A5: =Jurisdiction_Inventory!B5
A6: =Jurisdiction_Inventory!B6
A7: =Jurisdiction_Inventory!B7
A8: =Jurisdiction_Inventory!B8
A9: =Jurisdiction_Inventory!B9
A10: =Jurisdiction_Inventory!B10
A11: =Jurisdiction_Inventory!B11
A12: =Jurisdiction_Inventory!B12
A13: =Jurisdiction_Inventory!B13
A14: =Jurisdiction_Inventory!B14
A15: =Jurisdiction_Inventory!B15
A16: =Jurisdiction_Inventory!B16
... A34: =Jurisdiction_Inventory!B34

Sheet Primary_Filing_Prep
A1: PRIMARY FILING PREPARATION CHECKLIST
A3: # | B3: Check Item | C3: Status | D3: Date Completed | E3: Notes
A4: 1 | B4: Primary filing jurisdiction identified and confirmed
A5: 2 | B5: GIR Calculator completed for full MNE group
A6: 3 | B6: All jurisdictional data validated and reconciled
A7: 4 | B7: Safe harbour elections documented and verified
A8: 5 | B8: XML file generated from Calculator
A9: 6 | B9: Schema validation passed (Tier 1)
A10: 7 | B10: Business rule validation passed (Tier 2-3)
A11: 8 | B11: Internal technical review completed
A12: 9 | B12: Legal/compliance review completed
A13: 10 | B13: Management sign-off obtained
A14: 11 | B14: File hash recorded (SHA-256)
A15: 12 | B15: Filing deadline confirmed
... A17: 14 | B17: Backup filing arrangements in place

Sheet XML_Preparation
A1: MULTI-JURISDICTION XML PREPARATION
A3: # | B3: Check Item | C3: Status | D3: Date Completed | E3: Notes
A4: 1 | B4: Secondary jurisdiction requirements documented
A5: 2 | B5: XML files prepared for each jurisdiction
A6: 3 | B6: Consistency verification across all files completed
A7: 4 | B7: Each XML validated against OECD schema (v1.0 Jan 2025)
A8: 5 | B8: File naming convention applied consistently
A9: 6 | B9: All files hashed and recorded in File Register
A10: 7 | B10: Character encoding verified (UTF-8)
A11: 8 | B11: File size within portal limits confirmed
A12: 9 | B12: Test submission performed (if available)

Sheet Submission_Tracker
A1: SUBMISSION TRACKER
A2: Track all GIR and notification submissions across jurisdictions
A4: Jurisdiction | B4: Filing Type | C4: Filing Entity | D4: Submission Date | E4: Target Deadline | F4: Reference Number | G4: Status | H4: Confirmation Received? | I4: Confirmation Archived? | J4: Filed By | K4: Notes
A5: =Jurisdiction_Inventory!B5
A6: =Jurisdiction_Inventory!B6
A7: =Jurisdiction_Inventory!B7
A8: =Jurisdiction_Inventory!B8
A9: =Jurisdiction_Inventory!B9
A10: =Jurisdiction_Inventory!B10
A11: =Jurisdiction_Inventory!B11
A12: =Jurisdiction_Inventory!B12
A13: =Jurisdiction_Inventory!B13
A14: =Jurisdiction_Inventory!B14
A15: =Jurisdiction_Inventory!B15
A16: =Jurisdiction_Inventory!B16
... A34: =Jurisdiction_Inventory!B34

Sheet QDMTT_Returns
A1: QDMTT AND DOMESTIC RETURNS TRACKER
A3: Jurisdiction | B3: Return Type | C3: Filing Entity | D3: Tax Liability (EUR) | E3: Submission Date | F3: Reference Number | G3: Status | H3: Payment Amount (EUR) | I3: Payment Date | J3: Payment Reference
A36: SUMMARY
A37: Total Tax Liability: | B37: =SUMIF(D4:D33,">0",D4:D33)
A38: Total Payments Made: | B38: =SUMIF(H4:H33,">0",H4:H33)

Sheet Post_Filing_Verification
A1: POST-FILING VERIFICATION CHECKLIST
A3: # | B3: Check Item | C3: Status | D3: Date Completed | E3: Verified By
A4: 1 | B4: All primary GIR submissions confirmed accepted
A5: 2 | B5: All notifications (ORN) confirmed accepted
A6: 3 | B6: All QDMTT/domestic returns submitted and confirmed
A7: 4 | B7: All payments made by deadline
A8: 5 | B8: MCAA exchange confirmed (where trackable)
A9: 6 | B9: Receipts/confirmations archived for all filings
A10: 7 | B10: File register updated with all submission details
A11: 8 | B11: Internal stakeholders notified of completion
A12: 9 | B12: Authority queries responded to (if any)
A13: 10 | B13: Audit file documentation complete
A14: 11 | B14: Year 2+ planning notes documented
A15: 12 | B15: Process improvement items recorded

Sheet Amendment_Tracker
A1: AMENDMENT COORDINATION TRACKER
A3: # | B3: Check Item / Jurisdiction | C3: Amendment Reason | D3: Status | E3: Original Filing Ref | F3: Amendment Filing Ref | G3: Amendment Date | H3: Affected Jurisdictions | I3: Notes
A4: 1 | B4: Amendment scope identified (which jurisdictions affected)
A5: 2 | B5: Corrected XML prepared for each affected jurisdiction
A6: 3 | B6: Consistency verified across amended files
A7: 4 | B7: Amendment filed in primary jurisdiction first
A8: 5 | B8: Secondary jurisdictions notified/amended
A9: 6 | B9: All amendment receipts obtained and archived
A12: AMENDMENT LOG
A13: # | B13: Jurisdiction | C13: Amendment Reason | D13: Status | E13: Original Filing Ref | F13: Amendment Filing Ref | G13: Amendment Date | H13: Filed By | I13: Notes
A14: 1
A15: 2
A16: 3
A17: 4
A18: 5
A19: 6
A20: 7
A21: 8
A22: 9
A23: 10
A24: 11
A25: 12
... A28: 15

Sheet Data_Consistency
A1: DATA CONSISTENCY VERIFICATION
A2: Ensure data consistency across all multi-jurisdiction filings
A4: # | B4: Verification Item | C4: Status | D4: Date Verified | E4: Verified By
A5: 1 | B5: GIR total top-up tax reconciles to sum of domestic returns
A6: 2 | B6: Entity coverage consistent across all filings
A7: 3 | B7: Covered taxes reconcile to local tax filings
A8: 4 | B8: Ownership percentages consistent across all GIRs
A9: 5 | B9: GloBE Income/Loss consistent across jurisdictions
A10: 6 | B10: SBIE calculations consistent
A11: 7 | B11: Currency conversions applied consistently
A12: 8 | B12: Safe harbour elections consistent across filings
A13: 9 | B13: Entity names and identifiers match across all filings
A14: 10 | B14: Intercompany transactions properly eliminated
A15: 11 | B15: No data conflicts identified between primary and secondary filings
A16: 12 | B16: Reconciliation to CbCR data (where transitional safe harbour applies)
... A18: 14 | B18: Prior period comparisons reviewed for consistency
A21: RECONCILIATION SUMMARY
A23: Total Top-Up Tax per GIR (EUR):
A24: Sum of Domestic Returns (EUR):
A25: Difference: | C25: =IF(AND(ISNUMBER(C23),ISNUMBER(C24)),C23-C24,"")
A26: Explanation of Difference:

Sheet Sign_Off
A1: SIGN-OFF AND CERTIFICATION
A3: COMPLETION STATUS
A5: Fiscal Year: | B5: =Group_Info!B8&" to "&Group_Info!B9
A6: MNE Group: | B6: =Group_Info!B3
A8: All Filings Complete:
A10: CERTIFICATION
A12: I confirm that all Pillar Two filing obligations across all jurisdictions for the above fiscal year have been properly coordinated and completed. All GIR data is accurate and consistent across all filings to the best of my knowledge.
A16: SIGN-OFF
A18: Role | B18: Name | C18: Signature | D18: Date
A19: Prepared By (Group Tax Manager):
A20: Reviewed By (Head of Tax):
A21: Approved By (CFO / Tax Director):
A24: NOTES AND EXCEPTIONS
A26: Document any issues, exceptions, pending items, or matters for follow-up:
