Workbook

Sheet Dashboard
A1: CONSTITUENT ENTITY DATABASE
A2: Per OECD GloBE Information Return Section 1.3 - January 2025
A4: ENTITY SUMMARY
A6: Total Entities: | B6: =COUNTA(Entities!A:A)-1 | D6: VALIDATION STATUS
A7: In-Scope Entities: | B7: =COUNTIF(Entities!Q:Q,"In-Scope")
A8: Excluded Entities: | B8: =COUNTIF(Entities!AK:AK,"Yes") | D8: Validated: | E8: =COUNTIF(Entities!BV:BV,"Validated")
A9: Flow-Through Entities: | B9: =COUNTIF(Entities!AM:AM,"Yes") | D9: Pending Validation: | E9: =COUNTIF(Entities!BV:BV,"Pending")
D10: Validation Errors: | E10: =COUNTIF(Entities!BV:BV,"Error")
A11: ENTITY TYPE BREAKDOWN
A13: UPE (Ultimate Parent): | B13: =COUNTIF(Entities!P:P,"UPE")
A14: Constituent Entities: | B14: =COUNTIF(Entities!P:P,"CE")
A15: Permanent Establishments: | B15: =COUNTIF(Entities!P:P,"PE")
A16: Joint Ventures: | B16: =COUNTIF(Entities!AS:AS,"Yes")
A17: Minority-Owned CEs: | B17: =COUNTIF(Entities!AV:AV,"Yes")
A18: Investment Entities: | B18: =COUNTIF(Entities!AQ:AQ,"Yes")
A20: JURISDICTION SUMMARY
A22: Total Jurisdictions: | B22: =SUMPRODUCT(1/COUNTIF(Entities!D:D,Entities!D:D))-1
A23: QIIR Jurisdictions: | B23: =COUNTIF(Entities!AC:AC,"Yes")
A24: UTPR Jurisdictions: | B24: =COUNTIF(Entities!AF:AF,"Yes")
A25: QDMTT Jurisdictions: | B25: =COUNTIF(Entities!AI:AI,"Yes")
A27: SBIE CALCULATION INPUTS
A29: Total Employees: | B29: =SUM(Entities!BO:BO)
A30: Total Tangible Assets: | B30: =SUM(Entities!BP:BP)
A31: Total Payroll Costs: | B31: =SUM(Entities!BQ:BQ)

Sheet Entities
A1: Entity_ID | B1: Legal_Name | C1: Trading_Name | D1: Country_Code | E1: Country_Name | F1: TIN | G1: TIN_Type | H1: TIN_Issued_By | I1: Address_Street | J1: Address_City | K1: Address_Region | L1: Address_PostCode | M1: Address_Country | N1: Date_of_Incorporation | O1: Legal_Form | P1: Entity_Type_GloBE | Q1: GloBE_Status | R1: GloBE_Status_Pre_Change | S1: Ownership_Pct_Direct | T1: Immediate_Parent_ID | U1: Immediate_Parent_Name | V1: UPE_Ownership_Pct | W1: Ownership_Chain | X1: Functional_Currency | Y1: Reporting_Currency | Z1: Fiscal_Year_End | AA1: Fiscal_Year_Start | AB1: Main_Activity | AC1: NACE_Code | AD1: LEI | AE1: QIIR_In_Jurisdiction | AF1: QIIR_Applicable_To_CE | AG1: QIIR_Parent_Entity | AH1: UTPR_In_Jurisdiction | AI1: UTPR_Applicable | AJ1: UTPR_Taxing_Jurisdiction | AK1: QDMTT_In_Jurisdiction | AL1: Excluded_Entity | AM1: Exclusion_Type | AN1: Exclusion_Documentation | AO1: Flow_Through_Entity | AP1: Tax_Transparent_Entity | AQ1: Reverse_Hybrid_Entity | AR1: Stateless_Entity | AS1: Permanent_Establishment | AT1: PE_Main_Entity_ID | AU1: PE_Attribution_Method | AV1: Investment_Entity | AW1: Investment_Entity_Election | AX1: JV_Entity | AY1: JV_Group_ID | AZ1: JV_Election_Made | BA1: Minority_Owned_CE | BB1: MOCE_Ownership_Level | BC1: POPE_Entity | BD1: POPE_Subgroup_ID | BE1: Consolidation_Method | BF1: Accounting_Standard | BG1: In_Scope_for_GIR | BH1: Section_3_Required | BI1: Safe_Harbour_Eligible | BJ1: Safe_Harbour_Applied | BK1: Change_During_FY | BL1: Change_Date | BM1: Change_Type | BN1: Change_Description | BO1: Employee_Count | BP1: Tangible_Assets_NBV | BQ1: Payroll_Costs | BR1: Data_Source | BS1: Data_Owner | BT1: Last_Validated_Date | BU1: Validated_By | BV1: Validation_Status | BW1: Notes | BX1: Ownership_Check | BY1: SBIE_Payroll_CO | BZ1: SBIE_Asset_CO | CA1: Total_SBIE
A2: CE-001 | B2: GlobalCorp Holdings PLC | C2: GlobalCorp | D2: GB | E2: United Kingdom | F2: GB123456789 | G2: UTR | H2: HMRC | I2: 100 Finance Street | J2: London | K2: Greater London | L2: EC2A 1AB | M2: GB | N2: 2000-01-15 | O2: PLC | P2: UPE | Q2: In-Scope | S2: 100 | V2: 100 | W2: Direct | X2: GBP | Y2: EUR | Z2: 2024-12-31 | AA2: 2024-01-01 | AB2: Holding Company | AC2: 64.20 | AE2: Yes | AF2: Yes | AH2: Yes | AI2: Yes | AK2: Yes | AL2: No | AO2: No | AP2: No | AQ2: No | AR2: No | AS2: No | AV2: No | AX2: No | BA2: No | BC2: No | BE2: Full | BF2: IFRS | BG2: Yes | BH2: Yes | BI2: No | BJ2: No | BK2: No | BO2: 150 | BP2: 50000000 | BQ2: 15000000 | BR2: ERP | BS2: Tax Director | BT2: 2024-11-01 | BU2: J.Smith | BV2: Validated | BW2: Ultimate Parent | BX2: =IF(S2<=100,"Valid","Error") | BY2: =BQ2*0.098 | BZ2: =BP2*0.078 | CA2: =BY2+BZ2
A3: CE-002 | B3: GlobalCorp Germany GmbH | C3: GlobalCorp DE | D3: DE | E3: Germany | F3: DE987654321 | G3: Tax Number | H3: BZSt | I3: 50 Industrieweg | J3: Frankfurt | K3: Hessen | L3: 60311 | M3: DE | N3: 2005-06-01 | O3: GmbH | P3: CE | Q3: In-Scope | S3: 100 | T3: CE-001 | U3: GlobalCorp Holdings PLC | V3: 100 | W3: CE-001>CE-002 | X3: EUR | Y3: EUR | Z3: 2024-12-31 | AA3: 2024-01-01 | AB3: Manufacturing | AC3: 25.11 | AE3: Yes | AF3: Yes | AG3: CE-001 | AH3: Yes | AI3: Yes | AJ3: DE | AK3: Yes | AL3: No | AO3: No | AP3: No | AQ3: No | AR3: No | AS3: No | AV3: No | AX3: No | BA3: No | BC3: No | BE3: Full | BF3: IFRS | BG3: Yes | BH3: Yes | BI3: No | BJ3: No | BK3: No | BO3: 500 | BP3: 120000000 | BQ3: 35000000 | BR3: ERP | BS3: Local Finance | BT3: 2024-11-01 | BU3: M.Mueller | BV3: Validated | BX3: =IF(S3<=100,"Valid","Error") | BY3: =BQ3*0.098 | BZ3: =BP3*0.078 | CA3: =BY3+BZ3

Sheet Lookups
A1: Entity_Type | B1: GloBE_Status | C1: Yes_No | D1: Exclusion_Type | E1: Consolidation | F1: Validation_Status | G1: Country_Code
A2: UPE | B2: In-Scope | C2: Yes | D2: Pension Fund | E2: Full | F2: Validated | G2: GB
A3: CE | B3: Out-of-Scope | C3: No | D3: Non-Profit | E3: Proportionate | F3: Pending | G3: DE
A4: PE | B4: Excluded | D4: Government Entity | E4: Equity | F4: Error | G4: NL
A5: JV | B5: Pending Review | D5: International Organisation | E5: Not Consolidated | F5: Not Started | G5: FR
A6: MOCE | D6: Investment Fund | G6: IE
A7: Investment Entity | G7: LU
A8: Excluded | G8: SG
G9: AU
G10: JP
G11: KR
G12: CA
G13: CH
G14: US
G15: BE
G16: IT
G17: ES
G18: AT
G19: SE
G20: DK
G21: NO

Sheet SBIE_Rates
A1: SBIE TRANSITIONAL RATES
A3: Fiscal Year | B3: Payroll Rate | C3: Asset Rate | D3: Notes
A4: 2024 | B4: 0.098 | C4: 0.078 | D4: First year of implementation
A5: 2025 | B5: 0.096 | C5: 0.076
A6: 2026 | B6: 0.094 | C6: 0.074
A7: 2027 | B7: 0.092 | C7: 0.072
A8: 2028 | B8: 0.09 | C8: 0.07
A9: 2029 | B9: 0.082 | C9: 0.066
A10: 2030 | B10: 0.074 | C10: 0.062
A11: 2031 | B11: 0.066 | C11: 0.058
A12: 2032 | B12: 0.058 | C12: 0.054
A13: 2033 | B13: 0.05 | C13: 0.05 | D13: Steady state rates
A16: SBIE CALCULATION EXAMPLE
A18: Input | B18: Value | C18: Formula
A19: Eligible Payroll Costs | B19: 10000000
A20: Tangible Assets NBV | B20: 50000000
A21: Fiscal Year | B21: 2024
A23: Calculation
A24: Payroll Carve-out | B24: =B19*VLOOKUP(B21,A4:C13,2,FALSE) | C24: =Payroll × Rate
A25: Asset Carve-out | B25: =B20*VLOOKUP(B21,A4:C13,3,FALSE) | C25: =Assets × Rate
A26: Total SBIE | B26: =B24+B25 | C26: =Payroll CO + Asset CO
