Workbook

Sheet Dashboard
A1: GIR COMPLETION CALCULATOR
A2: Per January 2025 OECD GloBE Information Return Template
A4: OVERALL GIR COMPLETION
A6: Section 1 - MNE Group Information: | C6: =IF(COUNTA(Section_1!D:D)>0,COUNTIF(Section_1!M:M,"Complete")/COUNTA(Section_1!D:D),0)
A7: Section 2 - Safe Harbours & Exclusions: | C7: =IF(COUNTA(Section_2!D:D)>0,COUNTIF(Section_2!M:M,"Complete")/COUNTA(Section_2!D:D),0)
A8: Section 3 - GloBE Computations: | C8: =IF(COUNTA(Section_3!D:D)>0,COUNTIF(Section_3!M:M,"Complete")/COUNTA(Section_3!D:D),0)
A9: TOTAL GIR COMPLETION: | C9: =AVERAGE(C6:C8)
A11: ETR CALCULATION SUMMARY
A13: Jurisdiction | B13: GloBE Income | C13: Covered Taxes | D13: ETR | E13: Top-up % | F13: Status
A14: United Kingdom | B14: 0 | C14: 0 | D14: =IF(B14<>0,C14/B14,0) | E14: =MAX(0,0.15-D14) | F14: =IF(D14>=0.15,"No Top-up","Top-up Required")
A15: Germany | B15: 0 | C15: 0 | D15: =IF(B15<>0,C15/B15,0) | E15: =MAX(0,0.15-D15) | F15: =IF(D15>=0.15,"No Top-up","Top-up Required")
A16: Netherlands | B16: 0 | C16: 0 | D16: =IF(B16<>0,C16/B16,0) | E16: =MAX(0,0.15-D16) | F16: =IF(D16>=0.15,"No Top-up","Top-up Required")
A17: France | B17: 0 | C17: 0 | D17: =IF(B17<>0,C17/B17,0) | E17: =MAX(0,0.15-D17) | F17: =IF(D17>=0.15,"No Top-up","Top-up Required")
A18: Ireland | B18: 0 | C18: 0 | D18: =IF(B18<>0,C18/B18,0) | E18: =MAX(0,0.15-D18) | F18: =IF(D18>=0.15,"No Top-up","Top-up Required")
A21: SBIE TRANSITIONAL RATES
A23: Fiscal Year | B23: Payroll Rate | C23: Asset Rate
A24: 2024 | B24: 9.8% | C24: 7.8%
A25: 2025 | B25: 9.6% | C25: 7.6%
A26: 2026 | B26: 9.4% | C26: 7.4%
A27: 2027 | B27: 9.2% | C27: 7.2%
A28: 2028 | B28: 9.0% | C28: 7.0%
A29: 2029 | B29: 8.2% | C29: 6.6%
A30: 2030 | B30: 7.4% | C30: 6.2%
A31: 2031 | B31: 6.6% | C31: 5.8%
A32: 2032 | B32: 5.8% | C32: 5.4%
A33: 2033+ | B33: 5.0% | C33: 5.0%

Sheet Section_1
A1: GIR SECTION 1 - MNE GROUP INFORMATION
A3: Row | B3: Sub-Section | C3: XML Element | D3: Field Name | E3: Description | F3: Data Type | G3: Required | H3: Validation Rule | I3: Input Value | J3: Calculated Value | K3: Source | L3: Owner | M3: Status | N3: Notes
A4: 1 | B4: 1.1 | C4: FilingCE/Name | D4: Filing CE Name | E4: Legal name of Filing Constituent Entity | F4: String | G4: Yes | M4: Not Started
A5: 2 | B5: 1.1 | C5: FilingCE/TIN | D5: Filing CE TIN | E5: Tax ID of Filing CE | F5: String | G5: Yes | M5: Not Started
A6: 3 | B6: 1.1 | C6: FilingCE/Jurisdiction | D6: Filing CE Jurisdiction | E6: Country code of Filing CE | F6: CountryCode | G6: Yes | M6: Not Started
A7: 4 | B7: 1.2 | C7: UPE/Name | D7: UPE Name | E7: Ultimate Parent Entity name | F7: String | G7: Yes | M7: Not Started
A8: 5 | B8: 1.2 | C8: UPE/TIN | D8: UPE TIN | E8: Tax ID of UPE | F8: String | G8: Yes | M8: Not Started
A9: 6 | B9: 1.2 | C9: UPE/Jurisdiction | D9: UPE Jurisdiction | E9: Country code of UPE | F9: CountryCode | G9: Yes | M9: Not Started
A10: 7 | B10: 1.3 | C10: MNEGroup/Name | D10: Group Name | E10: Name of MNE Group | F10: String | G10: Yes | M10: Not Started
A11: 8 | B11: 1.3 | C11: MNEGroup/FiscalYearEnd | D11: Fiscal Year End | E11: End date of reporting period | F11: Date | G11: Yes | M11: Not Started
A12: 9 | B12: 1.3 | C12: MNEGroup/Currency | D12: Reporting Currency | E12: Currency for GIR amounts | F12: Currency | G12: Yes | M12: Not Started
A13: 10 | B13: 1.4 | C13: ConstituentEntities/Count | D13: CE Count | E13: Number of Constituent Entities | F13: Integer | G13: Yes | M13: Not Started
A16: SECTION 1 SUMMARY
A17: Total Fields: | B17: =COUNTA(D4:D13)
A18: Completed: | B18: =COUNTIF(M4:M13,"Complete")
A19: Completion %: | B19: =IF(B17>0,B18/B17,0)

Sheet Section_2
A1: GIR SECTION 2 - SAFE HARBOURS & EXCLUSIONS
A3: Row | B3: Sub-Section | C3: XML Element | D3: Field Name | E3: Description | F3: Data Type | G3: Required | H3: Validation Rule | I3: Input Value | J3: Calculated Value | K3: Source | L3: Owner | M3: Status | N3: Notes
A4: 1 | B4: 2.1 | C4: TSH/Jurisdiction | D4: TSH Jurisdiction | E4: Jurisdiction claiming TSH | F4: CountryCode | G4: Conditional | M4: Not Started
A5: 2 | B5: 2.1 | C5: TSH/Type | D5: TSH Type | E5: Type of TSH election | F5: Code | G5: Conditional | M5: Not Started
A6: 3 | B6: 2.1 | C6: TSH/Revenue | D6: TSH Revenue | E6: Revenue for TSH test | F6: Monetary | G6: Conditional | M6: Not Started
A7: 4 | B7: 2.1 | C7: TSH/Profit | D7: TSH Profit Before Tax | E7: PBT for TSH test | F7: Monetary | G7: Conditional | M7: Not Started
A8: 5 | B8: 2.1 | C8: TSH/SimplifiedETR | D8: Simplified ETR | E8: ETR for TSH test | F8: Percentage | G8: Conditional | M8: Not Started
A9: 6 | B9: 2.2 | C9: QDMTT/Jurisdiction | D9: QDMTT Jurisdiction | E9: Jurisdiction with QDMTT | F9: CountryCode | G9: Conditional | M9: Not Started
A10: 7 | B10: 2.2 | C10: QDMTT/TopUpTax | D10: QDMTT Top-up Tax | E10: QDMTT amount paid | F10: Monetary | G10: Conditional | M10: Not Started
A11: 8 | B11: 2.3 | C11: Exclusions/Type | D11: Exclusion Type | E11: Type of excluded entity | F11: Code | G11: Conditional | M11: Not Started
A12: 9 | B12: 2.3 | C12: Exclusions/Entity | D12: Excluded Entity | E12: Name of excluded entity | F12: String | G12: Conditional | M12: Not Started
A15: TRANSITIONAL SAFE HARBOUR TEST
A17: Test Type | B17: Threshold | C17: Input Value | D17: Result
A18: De Minimis Test (Revenue) | B18: < EUR 10m | C18: 0 | D18: =IF(C18<10000000,"PASS","FAIL")
A19: De Minimis Test (PBT) | B19: < EUR 1m loss | C19: 0 | D19: =IF(C19<1000000,"PASS","FAIL")
A20: Simplified ETR Test | B20: >= Transition Rate | C20: 0 | D20: =IF(C20>=0.15,"PASS","FAIL")
A21: Routine Profits Test | B21: PBT <= SBIE | C21: 0 | D21: =IF(C21<=0,"PASS","FAIL")

Sheet Section_3
A1: GIR SECTION 3 - GloBE COMPUTATIONS (Per Jurisdiction)
A3: Row | B3: Sub-Section | C3: XML Element | D3: Field Name | E3: Description | F3: Data Type | G3: Input GBP | H3: Input EUR | I3: Calculated | J3: Formula | K3: Validation | L3: Source | M3: Status | N3: Notes
A4: 1 | B4: 3.1 | C4: GloBEIncome/FinancialAccountingNetIncome | D4: Net Income/Loss | E4: Financial accounting net income | F4: Monetary | M4: Not Started
A5: 2 | B5: 3.1 | C5: GloBEIncome/AdjustmentsTotal | D5: Total Adjustments | E5: Sum of all GloBE adjustments | F5: Monetary | M5: Not Started
A6: 3 | B6: 3.1 | C6: GloBEIncome/GloBENetIncome | D6: GloBE Net Income | E6: Net Income + Adjustments | F6: Monetary | I6: =G4+G5 | J6: =G4+G5 | M6: Not Started
A7: 4 | B7: 3.2 | C7: CoveredTaxes/CurrentTaxExpense | D7: Current Tax Expense | E7: Current year tax expense | F7: Monetary | M7: Not Started
A8: 5 | B8: 3.2 | C8: CoveredTaxes/DeferredTaxAdjustment | D8: Deferred Tax Adjustment | E8: DTL/DTA adjustments | F8: Monetary | M8: Not Started
A9: 6 | B9: 3.2 | C9: CoveredTaxes/TotalAdjustedCoveredTaxes | D9: Adjusted Covered Taxes | E9: Total adjusted covered taxes | F9: Monetary | I9: =G7+G8 | J9: =G7+G8 | M9: Not Started
A10: 7 | B10: 3.3 | C10: ETR/JurisdictionalETR | D10: Jurisdictional ETR | E10: Covered Taxes / GloBE Income | F10: Percentage | I10: =IF(I6<>0,I9/I6,0) | J10: Covered Taxes / GloBE Income | M10: Not Started
A11: 8 | B11: 3.4 | C11: SBIE/EligiblePayrollCosts | D11: Eligible Payroll | E11: Eligible payroll costs | F11: Monetary | M11: Not Started
A12: 9 | B12: 3.4 | C12: SBIE/EligibleTangibleAssets | D12: Eligible Assets | E12: NBV of tangible assets | F12: Monetary | M12: Not Started
A13: 10 | B13: 3.4 | C13: SBIE/PayrollCarveOut | D13: Payroll Carve-out | E13: Payroll × Transitional Rate | F13: Monetary | I13: =G11*0.098 | J13: Payroll × 9.8% | M13: Not Started
A14: 11 | B14: 3.4 | C14: SBIE/AssetCarveOut | D14: Asset Carve-out | E14: Assets × Transitional Rate | F14: Monetary | I14: =G12*0.078 | J14: Assets × 7.8% | M14: Not Started
A15: 12 | B15: 3.4 | C15: SBIE/TotalSBIE | D15: Total SBIE | E15: Sum of carve-outs | F15: Monetary | I15: =I13+I14 | J15: Payroll CO + Asset CO | M15: Not Started
A16: 13 | B16: 3.5 | C16: TopUp/ExcessProfit | D16: Excess Profit | E16: GloBE Income - SBIE | F16: Monetary | I16: =MAX(0,I6-I15) | J16: GloBE Income - SBIE | M16: Not Started
A17: 14 | B17: 3.5 | C17: TopUp/TopUpPercentage | D17: Top-up Percentage | E17: 15% - ETR | F17: Percentage | I17: =MAX(0,0.15-I10) | J17: 15% - ETR | M17: Not Started
A18: 15 | B18: 3.5 | C18: TopUp/JurisdictionalTopUpTax | D18: Jurisdictional Top-up | E18: Excess Profit × Top-up % | F18: Monetary | I18: =I16*I17 | J18: Excess Profit × Top-up % | M18: Not Started
A19: 16 | B19: 3.6 | C19: Allocation/IIRAmount | D19: IIR Allocation | E19: IIR allocated amount | F19: Monetary | M19: Not Started
A20: 17 | B20: 3.6 | C20: Allocation/UTPRAmount | D20: UTPR Allocation | E20: UTPR allocated amount | F20: Monetary | M20: Not Started
A21: 18 | B21: 3.6 | C21: Allocation/QDMTTCredit | D21: QDMTT Credit | E21: QDMTT paid (credit) | F21: Monetary | M21: Not Started

Sheet Validation
A1: GIR VALIDATION CHECKLIST
A3: Validation Check | B3: Expected | C3: Actual | D3: Result | E3: Notes
A4: ETR Calculation Check | B4: =Covered Taxes / GloBE Income | C4: =Section_3!I10 | D4: =IF(C4=B4,"PASS","CHECK")
A5: SBIE Total Check | B5: =Payroll CO + Asset CO | C5: =Section_3!I15 | D5: =IF(C5=B5,"PASS","CHECK")
A6: Top-up % Check | B6: =MAX(0, 15% - ETR) | C6: =Section_3!I17 | D6: =IF(C6>=0,"PASS","CHECK")
A7: Excess Profit Check | B7: =GloBE Income - SBIE (>=0) | C7: =Section_3!I16 | D7: =IF(C7>=0,"PASS","CHECK")
A8: All Required Fields Complete | B8: =100% | C8: =Dashboard!C9 | D8: =IF(C8>=1,"PASS","INCOMPLETE")
A9: Section 1 Complete | B9: =100% | C9: =Dashboard!C6 | D9: =IF(C9>=1,"PASS","INCOMPLETE")
A10: Section 2 Complete | B10: =100% | C10: =Dashboard!C7 | D10: =IF(C10>=1,"PASS","INCOMPLETE")
A11: Section 3 Complete | B11: =100% | C11: =Dashboard!C8 | D11: =IF(C11>=1,"PASS","INCOMPLETE")
